spacetrack_files/__init__.py
spacetrack_files/api.py
spacetrack_files/files.py
spacetrack_files-0.0.3.dist-info/LICENSE
spacetrack_files-0.0.3.dist-info/METADATA
spacetrack_files-0.0.3.dist-info/WHEEL
spacetrack_files-0.0.3.dist-info/top_level.txt
spacetrack_files-0.0.3.dist-info/RECORD
