Metadata-Version: 2.1
Name: spacetrack-files
Version: 0.0.3
Summary: Simple module for ephemeris download and parse
Home-page: https://github.com/Flexlug/spacetrack_files
Author: Flexlug
Author-email: flexlug@outlook.com
Project-URL: GitHub, https://github.com/Flexlug
Keywords: spacetrack ephemeris starlink
Classifier: Programming Language :: Python :: 3.11
Classifier: License :: OSI Approved :: MIT License
Classifier: Operating System :: OS Independent
Requires-Python: >=3.7
License-File: LICENSE
Requires-Dist: requests >=2.31.0
Requires-Dist: pandas >=2.1.2
Requires-Dist: tqdm >=4.66.1
Requires-Dist: numpy >=1.26.1
